cp_snippets/__init__.py
cp_snippets/arrays.py
cp_snippets/bit_utils.py
cp_snippets/graphs.py
cp_snippets/io.py
cp_snippets/math_utils.py
cp_snippets/misc.py
cp_snippets/strings.py
cp_snippets/trees.py
cp_snippets-0.1.4.dist-info/licenses/LICENSE
cp_snippets-0.1.4.dist-info/METADATA
cp_snippets-0.1.4.dist-info/WHEEL
cp_snippets-0.1.4.dist-info/top_level.txt
cp_snippets-0.1.4.dist-info/RECORD
