Metadata-Version: 2.4
Name: cp-snippets
Version: 0.1.4
Summary: Small competitive programming concepts and utilities
Author: Lakshmi Srinivas
License: MIT
Requires-Python: >=3.8
License-File: LICENSE
Dynamic: license-file
